{"cameraMode":{"drawMode":0,"name":"Shaded","section":"Shading Mode"},"sceneLighting":true,"audioPlay":false,"sceneViewState":{"showFog":true,"showMaterialUpdate":false,"showSkybox":true,"showFlares":true,"showImageEffects":true,"showParticleSystems":true},"in2DMode":false,"pivot":{"x":-0.1397705078125,"y":0.75177001953125,"z":0.1972237229347229},"rotation":{"x":0.5051826238632202,"y":0.00009604563092580065,"z":0.0003141439228784293,"w":0.8631844520568848},"size":0.6866055727005005,"orthographic":false}